aio_client/__init__.py
aio_client/admin.py
aio_client/apps.py
aio_client/configs.py
aio_client/utils.py
aio_client/version.conf
aio_client/base/__init__.py
aio_client/base/const.py
aio_client/base/exceptions.py
aio_client/base/helpers.py
aio_client/base/signals.py
aio_client/base/tasks.py
aio_client/base/client/__init__.py
aio_client/base/client/sender.py
aio_client/base/client/tests/__init__.py
aio_client/base/client/tests/tests_sender.py
aio_client/base/models/__init__.py
aio_client/base/models/base.py
aio_client/base/models/enum.py
aio_client/base/models/log.py
aio_client/base/models/message.py
aio_client/base/models/tests/__init__.py
aio_client/base/models/tests/factory_log.py
aio_client/base/models/tests/factory_message.py
aio_client/base/models/tests/utils.py
aio_client/common/__init__.py
aio_client/common/configuration/__init__.py
aio_client/common/configuration/configuration.py
aio_client/consumer/__init__.py
aio_client/consumer/api.py
aio_client/consumer/const.py
aio_client/consumer/exceptions.py
aio_client/consumer/helpers.py
aio_client/consumer/tasks.py
aio_client/consumer/models/__init__.py
aio_client/consumer/models/consumer.py
aio_client/consumer/models/tests/__init__.py
aio_client/consumer/models/tests/factory_consumer.py
aio_client/consumer/tests/GetConsumerReceipt.json
aio_client/consumer/tests/GetConsumerRequest.json
aio_client/consumer/tests/__init__.py
aio_client/consumer/tests/request_data.py
aio_client/consumer/tests/tests_api.py
aio_client/consumer/tests/tests_helpers.py
aio_client/migrations/0001_initial.py
aio_client/migrations/0002_auto_20181026_1115.py
aio_client/migrations/0003_auto_20190201_0530.py
aio_client/migrations/0004_auto_20200703_1536.py
aio_client/migrations/0005_auto_20200703_1550.py
aio_client/migrations/0006_auto_20201109_0917.py
aio_client/migrations/0007_auto_20201113_2248.py
aio_client/migrations/0008_auto_20201209_1503.py
aio_client/migrations/0009_auto_20201210_1609.py
aio_client/migrations/0010_auto_20210416_1519.py
aio_client-1.14.0.dist-info/METADATA
aio_client-1.14.0.dist-info/WHEEL
aio_client-1.14.0.dist-info/dependency_links.txt
aio_client-1.14.0.dist-info/top_level.txt
aio_client-1.14.0.dist-info/RECORD
