Metadata-Version: 2.4
Name: aio-client
Version: 1.14.0
Summary: AIO-клиент
Author: BARS Group
Author-email: education_dev@bars-open.ru
Keywords: django СМЭВ3
Requires-Dist: six
Requires-Dist: requests<3,>=2.4.2
Requires-Dist: pyyaml
Requires-Dist: raven
Requires-Dist: sentry-sdk
Requires-Dist: yadic<1,>=0.1.12.6
Requires-Dist: Django>=3.1.0
Requires-Dist: m3-builder<2,>=1.2
Dynamic: author
Dynamic: author-email
Dynamic: description
Dynamic: description-content-type
Dynamic: keywords
Dynamic: requires-dist
Dynamic: summary
